octopus_python_client/__init__.py
octopus_python_client/actions.py
octopus_python_client/common.py
octopus_python_client/config.py
octopus_python_client/constants.py
octopus_python_client/deployment_processes.py
octopus_python_client/hello_world.py
octopus_python_client/main.py
octopus_python_client/migration.py
octopus_python_client/projects.py
octopus_python_client/release_deployment.py
octopus_python_client/configurations/configuration.json
octopus_python_client/configurations/source_server.json
octopus_python_client/configurations/system_config.json
octopus_python_client/gui/__init__.py
octopus_python_client/gui/actions_widgets.py
octopus_python_client/gui/common_widgets.py
octopus_python_client/gui/main_gui.py
octopus_python_client/gui/options_widgets.py
octopus_python_client/gui/servers_widgets.py
octopus_python_client/gui/spaces_widgets.py
octopus_python_client/gui/submit_widgets.py
octopus_python_client/gui/wizard.py
octopus_python_client/utilities/__init__.py
octopus_python_client/utilities/get_pypi_version.py
octopus_python_client/utilities/helper.py
octopus_python_client/utilities/send_requests_to_octopus.py
octopus_python_client-2.9.6.dist-info/LICENSE
octopus_python_client-2.9.6.dist-info/METADATA
octopus_python_client-2.9.6.dist-info/WHEEL
octopus_python_client-2.9.6.dist-info/entry_points.txt
octopus_python_client-2.9.6.dist-info/top_level.txt
octopus_python_client-2.9.6.dist-info/RECORD
