Metadata-Version: 2.1
Name: octopus-python-client
Version: 2.9.6
Summary: Python script & GUI to manage Octopus deploy servers through the Octopus Restful APIs
Home-page: https://github.com/tableau/octopus-python-client
Author: Tony Li
Author-email: tonybest@gmail.com
License: UNKNOWN
Platform: UNKNOWN
Requires-Dist: requests (>=2.20.0)
Requires-Dist: PyYAML (>=5.1)
Requires-Dist: urllib3
